sbx_conllu/__init__.py
sbx_conllu/conllu_import.py
sbx_conllu/metadata.yaml
sbx_conllu/py.typed
sparv_sbx_conllu-0.3.0.dist-info/WHEEL
sparv_sbx_conllu-0.3.0.dist-info/entry_points.txt
sparv_sbx_conllu-0.3.0.dist-info/METADATA
sparv_sbx_conllu-0.3.0.dist-info/RECORD
