Metadata-Version: 2.3
Name: sparv-sbx-conllu
Version: 0.3.0
Summary: Add your description here
Author: Språkbanken Text
Author-email: Språkbanken Text <sb-info@svenska.gu.se>
Classifier: Development Status :: 3 - Alpha
Classifier: Intended Audience :: Developers
Classifier: License :: OSI Approved :: MIT License
Classifier: Operating System :: Unix
Classifier: Operating System :: POSIX
Classifier: Programming Language :: Python :: 3.11
Classifier: Programming Language :: Python :: 3.12
Classifier: Programming Language :: Python :: 3.13
Classifier: Programming Language :: Python :: 3.14
Classifier: Programming Language :: Python :: Implementation :: CPython
Classifier: Topic :: Utilities
Requires-Dist: conllu>=6.0.0
Requires-Dist: setuptools>=80.9.0
Requires-Dist: sparv>=5.3.1
Requires-Python: >=3.11
Project-URL: Changelog, https://github.com/spraakbanken/sparv-sbx-conllu/blob/main/CHANGELOG.md
Project-URL: Homepage, https://spraakbanken.gu.se
Project-URL: Issues, https://github.com/spraakbanken/sparv-sbx-conllu/issues
Project-URL: Repository, https://github.com/spraakbanken/sparv-sbx-conllu
